LICENSE
MANIFEST.in
README.md
setup.cfg
setup.py
stdeb.cfg
./slapdcheck/__about__.py
./slapdcheck/__init__.py
./slapdcheck/base.py
./slapdcheck/cfg.py
./slapdcheck/html4.py
./slapdcheck/json.py
./slapdcheck/metrics.py
./slapdcheck/mrpe.py
./slapdcheck/openldap.py
./slapdcheck/state.py
./slapdcheck/zabbix.py
slapdcheck.egg-info/PKG-INFO
slapdcheck.egg-info/SOURCES.txt
slapdcheck.egg-info/dependency_links.txt
slapdcheck.egg-info/entry_points.txt
slapdcheck.egg-info/not-zip-safe
slapdcheck.egg-info/requires.txt
slapdcheck.egg-info/top_level.txt