Metadata-Version: 2.1
Name: slapdcheck
Version: 3.10.3
Summary: OpenLDAP monitoring check
Home-page: https://code.stroeder.com/ldap/slapdcheck
Author: Michael Stroeder
Author-email: michael@stroeder.com
Maintainer: Michael Stroeder
Maintainer-email: michael@stroeder.com
License: Apache-2.0
Download-URL: https://pypi.org/project/slapdcheck/#files
Project-URL: Source Code, https://code.stroeder.com/ldap/slapdcheck
Keywords: LDAP,OpenLDAP,slapd,monitoring
Platform: UNKNOWN
Classifier: Development Status :: 5 - Production/Stable
Classifier: Environment :: No Input/Output (Daemon)
Classifier: Intended Audience :: Information Technology
Classifier: Intended Audience :: System Administrators
Classifier: License :: OSI Approved :: Apache Software License
Classifier: Operating System :: POSIX
Classifier: Operating System :: POSIX :: Linux
Classifier: Operating System :: Unix
Classifier: Programming Language :: Python
Classifier: Programming Language :: Python :: 3
Classifier: Programming Language :: Python :: 3.6
Classifier: Programming Language :: Python :: 3.7
Classifier: Programming Language :: Python :: 3.8
Classifier: Programming Language :: Python :: 3.9
Classifier: Programming Language :: Python :: 3.10
Classifier: Programming Language :: Python :: 3 :: Only
Classifier: Topic :: System :: Monitoring
Classifier: Topic :: Software Development :: Libraries :: Python Modules
Classifier: Topic :: System :: Systems Administration
Classifier: Topic :: System :: Systems Administration :: Authentication/Directory
Classifier: Topic :: System :: Systems Administration :: Authentication/Directory :: LDAP
Requires-Python: >=3.6
Provides-Extra: metrics
Provides-Extra: zabbix
License-File: LICENSE
